api_youtube_uc/__init__.py
api_youtube_uc/exceptions.py
api_youtube_uc/selenium_driver.py
api_youtube_uc/youtube_api.py
api_youtube_uc-3.7.dist-info/LICENSE
api_youtube_uc-3.7.dist-info/METADATA
api_youtube_uc-3.7.dist-info/WHEEL
api_youtube_uc-3.7.dist-info/top_level.txt
api_youtube_uc-3.7.dist-info/RECORD
