Metadata-Version: 2.1
Name: api-youtube-uc
Version: 3.7
Summary: Upload shorts video to the YouTube channel(Selenium)(without API owned by Youtube)
Home-page: UNKNOWN
Author: ArtDanger
Author-email: danya221299@gmail.com
License: UNKNOWN
Keywords: python,selenium,youtube studio,youtube,api,upload,video,shorts video,auth google,undetected_chromedriver,uc,api_youtube_uc,api_youtube,youtube_api,api youtube,youtube api
Platform: UNKNOWN
Classifier: Development Status :: 1 - Planning
Classifier: Intended Audience :: Developers
Classifier: Programming Language :: Python :: 3
Classifier: Operating System :: Unix
Classifier: Operating System :: Microsoft :: Windows
License-File: LICENSE
Requires-Dist: undetected-chromedriver
Requires-Dist: pyperclip
